wm_win_tool.py
wm_win_tool-0.1.6.dist-info/LICENSE
wm_win_tool-0.1.6.dist-info/METADATA
wm_win_tool-0.1.6.dist-info/WHEEL
wm_win_tool-0.1.6.dist-info/entry_points.txt
wm_win_tool-0.1.6.dist-info/top_level.txt
wm_win_tool-0.1.6.dist-info/RECORD
