Metadata-Version: 2.1
Name: wm-win-tool
Version: 0.1.6
Summary: Store and restore desktops, geometries and shaded state of selected X11 windows
Home-page: https://github.com/frispete/wm-win-tool
Author: Hans-Peter Jansen
Author-email: hpj@urpla.net
License: GNU GPL 2 - see https://www.gnu.org/licenses/gpl2.txt for details
Platform: UNKNOWN
Classifier: Development Status :: 4 - Beta
Classifier: Intended Audience :: System Administrators
Classifier: License :: OSI Approved :: GNU General Public License v2 (GPLv2)
Classifier: Operating System :: POSIX
Classifier: Operating System :: POSIX :: Linux
Classifier: Programming Language :: Python :: 3.3
Classifier: Programming Language :: Python :: 3.4
Classifier: Programming Language :: Python :: 3.5
Classifier: Programming Language :: Python :: 3.6
Classifier: Programming Language :: Python :: 3.7
Classifier: Programming Language :: Python :: 3.8
Requires-Python: >=3
